./PKG-INFO
./README.md
./__init__.py
./pyproject.toml
./server.py
./setup.py
./.github/workflows/pypi-publish.yml
bach_google_search74-1.0.0.dist-info/METADATA
bach_google_search74-1.0.0.dist-info/WHEEL
bach_google_search74-1.0.0.dist-info/entry_points.txt
bach_google_search74-1.0.0.dist-info/RECORD
