Metadata-Version: 2.4
Name: bach-google_search74
Version: 1.0.0
Summary: RapidAPI: herosAPI/google-search74
Project-URL: Homepage, https://github.com/bachstudio/bach-google_search74
Project-URL: Repository, https://github.com/bachstudio/bach-google_search74
Project-URL: Documentation, https://github.com/bachstudio/bach-google_search74#readme
Requires-Python: >=3.10
Requires-Dist: fastmcp>=2.0.0
Requires-Dist: httpx>=0.25.0
Provides-Extra: dev
Requires-Dist: black>=23.0.0; extra == 'dev'
Requires-Dist: pytest>=7.0.0; extra == 'dev'
